{"author": null, "author_email": "aidtransparency@usaid.gov", "creator_user_id": "46f2459c-e1a6-42af-86bb-43d3d65293ae", "id": "c6d91f60-4eaa-4914-bca7-c02b16fac0c0", "isopen": true, "license_id": "cc-zero", "license_title": "Creative Commons CCZero", "license_url": "http://www.opendefinition.org/licenses/cc-zero", "maintainer": null, "maintainer_email": null, "metadata_created": "2017-04-27T19:09:56.824005", "metadata_modified": "2025-04-04T02:08:27.307772", "name": "usaid-my", "notes": "", "num_resources": 1, "num_tags": 0, "organization": {"id": "8c54d3ba-1da7-40a8-a1cb-598cfb1ba6c1", "name": "usaid", "title": "United States Agency for International Development (USAID)", "type": "organization", "description": "", "image_url": "https://upload.wikimedia.org/wikipedia/commons/thumb/1/17/USAID-Identity.svg/500px-USAID-Identity.svg.png", "created": "2017-04-06T18:22:55.941485", "is_organization": true, "approval_status": "approved", "state": "active"}, "owner_org": "8c54d3ba-1da7-40a8-a1cb-598cfb1ba6c1", "private": false, "state": "active", "title": "USAID - Malaysia", "type": "dataset", "url": null, "version": null, "extras": [{"key": "activity_count", "value": "5"}, {"key": "country", "value": "MY"}, {"key": "data_updated", "value": "2025-04-03 20:52:13"}, {"key": "filetype", "value": "activity"}, {"key": "iati_version", "value": "2.03"}, {"key": "language", "value": "en"}, {"key": "secondary_publisher", "value": ""}, {"key": "validation_status", "value": "Error"}], "resources": [{"cache_last_updated": null, "cache_url": null, "created": "2020-06-25T19:03:03.416068", "description": "", "format": "IATI-XML", "hash": "05198bfe756b78c7922afe10bfe44ad32884c334", "id": "963150a9-e9c2-47b9-840a-52d70b19d965", "last_modified": null, "metadata_modified": "2025-04-04T02:08:27.313850", "mimetype": "", "mimetype_inner": null, "name": null, "package_id": "c6d91f60-4eaa-4914-bca7-c02b16fac0c0", "position": 0, "resource_type": null, "revision_id": "19a77aab-c73d-4548-ab3c-f6087b28d7ca", "size": 35472, "state": "active", "url": "https://s3.amazonaws.com/files.explorer.devtechlab.com/iati-activities-Malaysia.xml", "url_type": null}], "tags": [], "groups": [], "relationships_as_subject": [], "relationships_as_object": []}