<?xml version="1.0"?>
<iati-activities version="2.02" generated-datetime="2018-10-09T09:25:05+00:00">
<!--Generated By AidStream-->
  <iati-activity last-updated-datetime="2018-10-09T09:25:05+00:00" xml:lang="en" default-currency="EUR" humanitarian="1" hierarchy="1" linked-data-uri="">
    <iati-identifier>ES-CIF-G81164105-NEF5AB</iati-identifier>
    <reporting-org type="21" ref="ES-CIF-G81164105">
      <narrative xml:lang="en">ACTION AGAINST HUNGER SPAIN</narrative>
      <narrative xml:lang="es">ACCI&#xD3;N CONTRA EL HAMBRE</narrative>
    </reporting-org>
    <title>
      <narrative>Emergency Wash response to stem the hepatitis E epidemic-Diffa Region</narrative>
    </title>
    <description type="1">
      <narrative>To distribute soaps and jerrycans, as well as to organize sensitization sessions on how to prevent Hepatits E, in 3 sites/villages where Action Against Hunger already implements WASH activities. These activities are focused on prevention of this disease in order to prevent the rapid spread of the virus and to contain the epidemic as fast as possible.</narrative>
    </description>
    <participating-org ref="GB-CHC-1047501" type="21" role="4">
      <narrative xml:lang="en">Action Against Hunger</narrative>
    </participating-org>
    <participating-org ref="ES-CIF-G81164105" type="21" role="4">
      <narrative xml:lang="en">ACTION AGAINST HUNGER SPAIN</narrative>
      <narrative xml:lang="es">ACCI&#xD3;N CONTRA EL HAMBRE</narrative>
    </participating-org>
    <other-identifier ref="XI-PB-G-81164105" type="B1"/>
    <activity-status code="3"/>
    <activity-date type="2" iso-date="2017-05-06"/>
    <activity-date type="4" iso-date="2017-06-20"/>
    <recipient-country code="NE"/>
    <sector code="Water, Sanitation &amp; Hygiene" vocabulary="99" vocabulary-uri="https://www.accioncontraelhambre.org/en/what-we-do/lines-of-action/water-sanitation-and-hygiene"/>
    <budget type="1" status="2">
      <period-start iso-date="2017-05-06"/>
      <period-end iso-date="2017-06-20"/>
      <value currency="GBP" value-date="2017-05-06">35027</value>
    </budget>
  </iati-activity>
</iati-activities>
